{
  "words": [
    { "word": "masa", "level": "kolay", "definition": "Düz yüzeyi olan, eşya koymaya uygun nesne." },
    { "word": "kitap", "level": "kolay", "definition": "Bilgi ve eğlence kaynağı olan basılı eser." },
    { "word": "deniz", "level": "kolay", "definition": "Büyük su kütlesi." },
    { "word": "ev", "level": "kolay", "definition": "İnsanların yaşadığı bina." },
    { "word": "ağaç", "level": "kolay", "definition": "Odunsu gövdesi olan bitki." },
    { "word": "doğa", "level": "kolay", "definition": "Canlıların yaşadığı çevre." },
    { "word": "öğrenci", "level": "kolay", "definition": "Eğitim kurumlarına giden kişi." },
    { "word": "bilgisayar", "level": "orta", "definition": "Veri işleyen elektronik cihaz." },
    { "word": "araba", "level": "orta", "definition": "Ulaşım sağlayan motorlu araç." },
    { "word": "orman", "level": "orta", "definition": "Ağaçların yoğun olduğu geniş alan." },
    { "word": "güneş", "level": "orta", "definition": "Dünya'nın enerji kaynağı, parlak yıldız." },
    { "word": "yıldız", "level": "orta", "definition": "Gökyüzünde görülen parlak cisim." },
    { "word": "şehir", "level": "orta", "definition": "Çoğunlukla kentsel nüfusa sahip yerleşim yeri." },
    { "word": "teknoloji", "level": "orta", "definition": "Gelişmiş bilimsel uygulamaların alanı." },
    { "word": "mantık", "level": "orta", "definition": "Doğru düşünme sanatı." },
    { "word": "kültür", "level": "orta", "definition": "Toplumsal yaşamın değerleri ve gelenekleri." },
    { "word": "muhabbet", "level": "zor", "definition": "Samimi sohbet, hoş sohbet." },
    { "word": "fenomen", "level": "zor", "definition": "Kitleleri etkileyen kişi veya olay." },
    { "word": "sembol", "level": "zor", "definition": "Bir kavramın ya da durumun temsilcisi." },
    { "word": "devrim", "level": "zor", "definition": "Radikal toplumsal değişim hareketi." },
    { "word": "serüven", "level": "zor", "definition": "Genellikle macera dolu olaylar dizisi." },
    { "word": "entegrasyon", "level": "zor", "definition": "Bütünleşme, uyum süreci." },
    { "word": "özgürlük", "level": "zor", "definition": "Bağımsızlık ve serbestlik hali." },
    { "word": "yaratıcılık", "level": "zor", "definition": "Yeni fikirler oluşturma yeteneği." },
    { "word": "sosyoloji", "level": "zor", "definition": "Toplumu inceleyen sosyal bilim dalı." },
    { "word": "hikaye", "level": "kolay", "definition": "Sözel anlatı niteliğinde kısa öykü." },
    { "word": "çalışma", "level": "orta", "definition": "Emek gerektiren iş veya faaliyeti ifade eder." },
    { "word": "elektrik", "level": "orta", "definition": "Modern yaşamın temel enerji kaynağı." },
    { "word": "mimarlık", "level": "zor", "definition": "Bina tasarımı ve inşaat sanatı." },
    { "word": "psikoloji", "level": "zor", "definition": "İnsan davranışlarını ve zihinsel süreçleri inceleyen bilim dalı." },
    { "word": "bilgelik", "level": "zor", "definition": "Derin anlayış ve tecrübe sonucu ortaya çıkan akıl." },
    { "word": "sanat", "level": "orta", "definition": "Estetik değerlerin ve yaratıcılığın ifadesi." },
    { "word": "ekonomi", "level": "orta", "definition": "Kaynakların üretimi ve dağıtımını inceleyen sosyal bilim dalı." },
    { "word": "felsefe", "level": "zor", "definition": "Varlık ve düşünce üzerine derin sorgulama." },
    { "word": "yarış", "level": "kolay", "definition": "Rekabet duygusunu ifade eden etkinlik." },
    { "word": "müzik", "level": "kolay", "definition": "Seslerin uyumlu düzenlenmesi." },
    { "word": "edebiyat", "level": "orta", "definition": "Yazılı sanatın bütününü ifade eder." },
    { "word": "teori", "level": "zor", "definition": "Bilimsel açıklamaların temel varsayımı." },
    { "word": "algoritma", "level": "zor", "definition": "Problemlerin çözümünde kullanılan adım adım işlem dizisi." },
    { "word": "deneyim", "level": "orta", "definition": "Yaşanan olaylardan edinilen bilgi ve beceri." },
    { "word": "yaşam", "level": "kolay", "definition": "Canlı varlıkların tüm aktivitelerini ifade eder." },
    { "word": "mutluluk", "level": "orta", "definition": "Memnuniyet ve sevinç hali." },
    { "word": "gerçeklik", "level": "zor", "definition": "Olan biten, somut dünya hali." },
    { "word": "hayal", "level": "kolay", "definition": "Düşler ve hayal gücünün ifadesi." },
    { "word": "zihin", "level": "orta", "definition": "Düşünme, anlama yeteneğinin alanı." },
    { "word": "sevgi", "level": "kolay", "definition": "İnsanların birbirine duyduğu derin bağlılık ve şefkat." },
    { "word": "umut", "level": "orta", "definition": "Geleceğe dair pozitif beklenti ve inanç." },
    { "word": "adalet", "level": "orta", "definition": "Hak ve hukukun sağlanması, eşitlik ilkesi." },
    { "word": "sabır", "level": "kolay", "definition": "Zorluklar karşısında tahammül ve metanet gösterme yeteneği." },
    { "word": "özveri", "level": "zor", "definition": "Kendi çıkarlarını geri planda tutarak başkaları için fedakarlık yapma durumu." },
    { "word": "barış", "level": "kolay", "definition": "Uyum ve huzur içinde olma durumu." },
    { "word": "medeniyet", "level": "zor", "definition": "Bir toplumun maddi ve manevi varlıklarının tümü." },
    { "word": "vicdan", "level": "orta", "definition": "Kişinin iyi ile kötüyü ayırt etme yeteneği." },
    { "word": "hoşgörü", "level": "orta", "definition": "Anlayışlı ve müsamahalı davranma durumu." },
    { "word": "tevazu", "level": "zor", "definition": "Alçakgönüllülük, kibirsiz olma hali." },
    { "word": "merhamet", "level": "orta", "definition": "Başkalarının acısını paylaşma duygusu." },
    { "word": "vefa", "level": "zor", "definition": "Sevgi ve dostlukta bağlılık, sadakat gösterme." },
    { "word": "cesaret", "level": "orta", "definition": "Güç veya tehlikeli bir işe girişirken duyulan korkunun üstesinden gelme." },
    { "word": "huzur", "level": "kolay", "definition": "Dirlik, rahatlık, iç rahatlığı durumu." },
    { "word": "fazilet", "level": "zor", "definition": "Olgunluk, erdemlilik, üstün ahlaki değer." },
    { "word": "emek", "level": "kolay", "definition": "Bir işi yapmak için harcanan güç, çaba." },
    { "word": "irade", "level": "orta", "definition": "Bir şeyi yapıp yapmamaya karar verme gücü." },
    { "word": "tefekkür", "level": "zor", "definition": "Düşünme, derin düşünce." },
    { "word": "azim", "level": "orta", "definition": "Kararlılık, bir işi yapmaktaki kesin karar." },
    { "word": "letafet", "level": "zor", "definition": "Hoşluk, güzellik, zariflik." },
    { "word": "bereket", "level": "orta", "definition": "Bolluk, gürlük, verimlilik durumu." },
    { "word": "feraset", "level": "zor", "definition": "Anlayış ve kavrayış kabiliyeti, sezgi gücü." },
    { "word": "sadakat", "level": "orta", "definition": "İçten bağlılık, sözünde durma." },
    { "word": "neşe", "level": "kolay", "definition": "Sevinç, mutluluk duygusu." },
    { "word": "hikmet", "level": "zor", "definition": "Bilgelik, her şeyin gerçek sebebini bilme." },
    { "word": "zarafet", "level": "zor", "definition": "İncelik, kibarlık, zerafet." },
    { "word": "saadet", "level": "orta", "definition": "Mutluluk, bahtiyarlık." },
    { "word": "gayret", "level": "orta", "definition": "Çalışma, çabalama, bir işi başarmak için gösterilen çaba." },
    { "word": "kalem", "level": "kolay", "definition": "Yazı yazmaya yarayan araç." },
    { "word": "ihtiram", "level": "zor", "definition": "Saygı gösterme, hürmet etme." },
    { "word": "basiret", "level": "zor", "definition": "Doğruyu yanlıştan ayırt etme yeteneği, uzağı görüş." },
    { "word": "liyakat", "level": "zor", "definition": "Bir kimsenin, bir işe uygunluğu, yaraşırlığı, değerliliği." },
    { "word": "merak", "level": "kolay", "definition": "Bir şeyi anlamak, öğrenmek için duyulan istek." },
    { "word": "sebat", "level": "orta", "definition": "Sözünden veya kararından dönmeme, kararlılık." },
    { "word": "nezaket", "level": "orta", "definition": "Başkalarına karşı saygılı ve incelikli davranma." }
  ]
}
